rnet_notify/__init__.py
rnet_notify/proxies_manager.py
rnet_notify/rnet_proxies_manager_client.py
rnet_notify-0.0.4.dist-info/METADATA
rnet_notify-0.0.4.dist-info/WHEEL
rnet_notify-0.0.4.dist-info/top_level.txt
rnet_notify-0.0.4.dist-info/RECORD
