Metadata-Version: 2.4
Name: rnet-notify
Version: 0.0.4
Summary: Sem descrição
Author-email: Naruto Uzumaki <naruto_uzumaki@gmail.com>
License-Expression: MIT
Project-URL: Homepage, https://github.com/jefersonAlbara/rnet-notify
Requires-Python: >=3.12
Requires-Dist: dataclasses_json
Requires-Dist: typing_extensions
Requires-Dist: rnet==3.0.0rc17
